{
    "actionOnStepFail": null, 
    "enabled": true, 
    "externalUuid4": "ebe3d531-24d2-4460-92ed-fd1c8608da74", 
    "interpreter": 2, 
    "interpreterCommand": "", 
    "interpreterScriptExt": null, 
    "interpreterScriptSyntax": "", 
    "key": "copywindowsefifilestowinpestagingonwindowsworker", 
    "name": "Copy Windows EFI Files to WinPE Staging on Windows Worker", 
    "osCredKey": "automationworkerwindowsuseradministrator", 
    "serverKey": "automationworkerwindowsnode", 
    "successExitCode": 0, 
    "timeout": 300, 
    "type": "com.servertribe.attune.tuples.StepWinRmTuple"
}