{
    "actionOnStepFail": null, 
    "concurrency": 1, 
    "enabled": true, 
    "externalUuid4": "0355573e-7772-4d71-8b1e-fe4f58a423dc", 
    "isBlueprint": false, 
    "key": "lindeletesetupexefromwinpestagingbootwimgroup", 
    "links": [
        {
            "order": 0, 
            "stepKey": "lincreatebootwimmountdirectory"
        }, 
        {
            "order": 50, 
            "stepKey": "linwimlibmountwinpestagingbootwim"
        }, 
        {
            "order": 100, 
            "stepKey": "lindeletesetupexefrombootwim"
        }, 
        {
            "order": 150, 
            "stepKey": "linwimlibunmountbootwim"
        }
    ], 
    "name": "LIN Delete setup.exe from winpe_staging boot.wim - Group", 
    "type": "com.servertribe.attune.tuples.StepGroupTuple"
}